{
  "main": {
    "id": "8c1376caddaea8c2",
    "type": "split",
    "children": [
      {
        "id": "dbe6cf417089d7ca",
        "type": "tabs",
        "children": [
          {
            "id": "7c9db248119eef91",
            "type": "leaf",
            "state": {
              "type": "markdown",
              "state": {
                "file": "00-overview/daily/2024-11-14/13_error_resolution_log.md",
                "mode": "source",
                "source": false
              },
              "icon": "lucide-file",
              "title": "13_error_resolution_log"
            }
          },
          {
            "id": "86138a37b0ac1dce",
            "type": "leaf",
            "state": {
              "type": "markdown",
              "state": {
                "file": "00-overview/daily/2024-11-14/002_legal_tems_analysis_νομική_ορολογία_πρότυπα.md",
                "mode": "source",
                "source": false
              },
              "icon": "lucide-file",
              "title": "002_legal_tems_analysis_νομική_ορολογία_πρότυπα"
            }
          }
        ],
        "currentTab": 1
      }
    ],
    "direction": "vertical"
  },
  "left": {
    "id": "49559e1011d8d9cf",
    "type": "split",
    "children": [
      {
        "id": "d2b9e422aba45927",
        "type": "tabs",
        "children": [
          {
            "id": "6098df49edddc3ab",
            "type": "leaf",
            "state": {
              "type": "file-explorer",
              "state": {
                "sortOrder": "alphabetical"
              },
              "icon": "lucide-folder-closed",
              "title": "Files"
            }
          },
          {
            "id": "70903ec9745d326e",
            "type": "leaf",
            "state": {
              "type": "search",
              "state": {
                "query": "",
                "matchingCase": false,
                "explainSearch": false,
                "collapseAll": false,
                "extraContext": false,
                "sortOrder": "alphabetical"
              },
              "icon": "lucide-search",
              "title": "Search"
            }
          },
          {
            "id": "471bbd9131fdebe9",
            "type": "leaf",
            "state": {
              "type": "bookmarks",
              "state": {},
              "icon": "lucide-bookmark",
              "title": "Bookmarks"
            }
          }
        ]
      }
    ],
    "direction": "horizontal",
    "width": 333.5
  },
  "right": {
    "id": "f30b73b7c7ee70a0",
    "type": "split",
    "children": [
      {
        "id": "337f7dd457e29d5b",
        "type": "tabs",
        "children": [
          {
            "id": "13b3d5aebaaa554c",
            "type": "leaf",
            "state": {
              "type": "backlink",
              "state": {
                "file": "00-overview/daily/obsidian-appearance.md",
                "collapseAll": false,
                "extraContext": false,
                "sortOrder": "alphabetical",
                "showSearch": false,
                "searchQuery": "",
                "backlinkCollapsed": false,
                "unlinkedCollapsed": true
              },
              "icon": "links-coming-in",
              "title": "Backlinks for obsidian-appearance"
            }
          },
          {
            "id": "039d40e8fd6427ec",
            "type": "leaf",
            "state": {
              "type": "outgoing-link",
              "state": {
                "file": "00-overview/daily/obsidian-appearance.md",
                "linksCollapsed": false,
                "unlinkedCollapsed": true
              },
              "icon": "links-going-out",
              "title": "Outgoing links from obsidian-appearance"
            }
          },
          {
            "id": "5d82984cec1cb85d",
            "type": "leaf",
            "state": {
              "type": "tag",
              "state": {
                "sortOrder": "frequency",
                "useHierarchy": true
              },
              "icon": "lucide-tags",
              "title": "Tags"
            }
          },
          {
            "id": "71f00209e7f541bd",
            "type": "leaf",
            "state": {
              "type": "outline",
              "state": {
                "file": "00-overview/daily/2024-11-14/002_legal_tems_analysis_νομική_ορολογία_πρότυπα.md"
              },
              "icon": "lucide-list",
              "title": "Outline of 002_legal_tems_analysis_νομική_ορολογία_πρότυπα"
            }
          }
        ],
        "currentTab": 3
      }
    ],
    "direction": "horizontal",
    "width": 200
  },
  "left-ribbon": {
    "hiddenItems": {
      "switcher:Open quick switcher": false,
      "graph:Open graph view": false,
      "canvas:Create new canvas": false,
      "daily-notes:Open today's daily note": false,
      "templates:Insert template": false,
      "command-palette:Open command palette": false,
      "obsidian-git:Open Git source control": false
    }
  },
  "active": "6098df49edddc3ab",
  "lastOpenFiles": [
    "00-overview/daily/2024-11-14/23_statistical_analysis_legal_cases.md",
    "00-overview/daily/2024-11-14/002_legal_tems_analysis_νομική_ορολογία_πρότυπα.md",
    "00-overview/daily/2024-11-14/22_requierement_analysis_strategic_plan.md",
    "00-overview/daily/2024-11-14/21_text_classification_anaysis report.md",
    "templates/040_tls_oo1_template.md",
    "templates/010_rns_001_template.md",
    "templates/006_dos_oo1_template.md",
    "templates/008_obsidian_appearance.md",
    "00-overview/daily/2024-11-14/15_project_analysis_current_status.md",
    "00-overview/daily/2024-11-14/16_preprocessing_analysis_pipeline.md",
    "templates/007_meeting_note.md",
    "00-overview/daily/2024-11-14/19_tls_NaN.md",
    "templates/004_design_doc.md",
    "00-overview/daily/2024-11-14/20_error_analusis_resolution_plan.md",
    "00-overview/daily/2024-11-14/18_modules_αναλυση_επιλυση.md",
    "00-overview/daily/2024-11-14/17_data_loading_process.md.md",
    "00-overview/daily/2024-11-14/10_citation_analysis_findings.md.md",
    "00-overview/daily/2024-11-14/09_preprocessing_setup.md.md",
    "00-overview/daily/2024-11-14/12_error_module_analysis.md",
    "00-overview/daily/2024-11-14/11_σύστημα_εξαγωγής_χαρακτηριστικών.md",
    "Screenshot 2024-11-14 120456.png",
    "Screenshot 2024-11-14 032618.png",
    "Screenshot 2024-11-14 123642.png",
    "Pasted image 20241114123645.png",
    "00-overview/daily/2024-11-14/02_text_preprocessing.ipynb.md",
    "00-overview/daily/2024-11-14/13_error_resolution_log.md",
    "00-overview/daily/2024-11-14/14_gpu_metrics_dev_analysis.md",
    "00-overview/daily/2024-11-14/02_vs_code_setup_guide.md",
    "01-specs/02_project_complete_specifications.md",
    "01-specs/01_project_specs.md",
    "03-impl/notebooks/05_optimization.ipynb",
    "03-impl/notebooks/04_initial_modeling.ipynb",
    "03-impl/notebooks/02_text_preprocessing.ipynb",
    "03-impl/notebooks/03_feature_engineering.ipynb",
    "03-impl/notebooks/01_eda_legal_text_classification-ipynb",
    "03-impl/notebooks",
    "00-overview/daily/2024-11-14",
    "00-overview/daily/2024-11-13",
    "00-overview/daily",
    "00-overview/daily"
  ]
}